reus/__init__.py
reus/setup.py
reus/teams.py
reus/util.py
reus/fbref/__init__.py
reus/fbref/fb_league_table.py
reus/fbref/fb_match_data.py
reus/fbref/fb_match_defensive_actions_stats.py
reus/fbref/fb_match_keeper_stats.py
reus/fbref/fb_match_lineups.py
reus/fbref/fb_match_metadata.py
reus/fbref/fb_match_misc_stats.py
reus/fbref/fb_match_passing_stats.py
reus/fbref/fb_match_passing_type_stats.py
reus/fbref/fb_match_possession_stats.py
reus/fbref/fb_match_shots.py
reus/fbref/fb_match_summary.py
reus/fbref/fb_match_summary_stats.py
reus/fbref/fb_match_team_stats.py
reus/fbref/fb_match_urls.py
reus/fbref/fb_player_match_logs_data.py
reus/fbref/fb_player_match_logs_defensive_actions.py
reus/fbref/fb_player_match_logs_gca_sca.py
reus/fbref/fb_player_match_logs_misc.py
reus/fbref/fb_player_match_logs_passing.py
reus/fbref/fb_player_match_logs_passing_type.py
reus/fbref/fb_player_match_logs_possession.py
reus/fbref/fb_player_match_logs_summary.py
reus/fbref/fb_player_scouting_report.py
reus/fbref/fb_season_fixture_urls.py
reus/fbref/fb_season_urls.py
reus/fbref/fb_team_advanced_keeper_stats.py
reus/fbref/fb_team_data.py
reus/fbref/fb_team_defensive_actions_stats.py
reus/fbref/fb_team_goal_sca_stats.py
reus/fbref/fb_team_keeper_stats.py
reus/fbref/fb_team_misc_stats.py
reus/fbref/fb_team_passing_stats.py
reus/fbref/fb_team_passing_type_stats.py
reus/fbref/fb_team_player_advanced_keeper_stats.py
reus/fbref/fb_team_player_data.py
reus/fbref/fb_team_player_defensive_actions_stats.py
reus/fbref/fb_team_player_goal_sca_stats.py
reus/fbref/fb_team_player_keeper_stats.py
reus/fbref/fb_team_player_misc_stats.py
reus/fbref/fb_team_player_passing_stats.py
reus/fbref/fb_team_player_passing_type_stats.py
reus/fbref/fb_team_player_playing_time_stats.py
reus/fbref/fb_team_player_possession_stats.py
reus/fbref/fb_team_player_shooting.py
reus/fbref/fb_team_player_shooting_stats.py
reus/fbref/fb_team_player_summary_stats.py
reus/fbref/fb_team_playing_time_stats.py
reus-1.1.7.dist-info/LICENSE
reus-1.1.7.dist-info/METADATA
reus-1.1.7.dist-info/WHEEL
reus-1.1.7.dist-info/top_level.txt
reus-1.1.7.dist-info/RECORD
