Metadata-Version: 2.1
Name: reus
Version: 1.1.7
Summary: A package that allows you scrape soccer information
Home-page: https://github.com/ian-shepherd/reus
Author: Ian Shepherd
License: UNKNOWN
Keywords: python,fbref,fotmob,transfermarkt,soccer,football
Platform: UNKNOWN
Classifier: Programming Language :: Python :: 3
Classifier: License :: OSI Approved :: MIT License
Classifier: Operating System :: OS Independent
Requires-Python: >=3.10
License-File: LICENSE
Requires-Dist: pandas (>=2.2.0)
Requires-Dist: numpy (>=1.26.4)
Requires-Dist: requests (>=2.23.0)
Requires-Dist: beautifulsoup4 (>=4.10.0)
